generata/__init__.py
generata/__main__.py
generata/generator.py
generata-0.0.2.dist-info/METADATA
generata-0.0.2.dist-info/WHEEL
generata-0.0.2.dist-info/entry_points.txt
generata-0.0.2.dist-info/top_level.txt
generata-0.0.2.dist-info/RECORD
