Metadata-Version: 2.1
Name: generata
Version: 0.0.2
Summary: Generate sample data
Home-page: https://github.com/praveentn/generata
Author: Praveen Narayan
Author-email: sigmoidptn@gmail.com
License: MIT
Platform: UNKNOWN
Classifier: License :: OSI Approved :: MIT License
Classifier: Programming Language :: Python :: 3
Classifier: Programming Language :: Python :: 3.8
Requires-Dist: numpy
Requires-Dist: pandas
